devboiler/__init__.py
devboiler/api.py
devboiler/cli.py
devboiler/templates/ci/github/python.yml.j2
devboiler/templates/docker/Dockerfile.node.j2
devboiler/templates/docker/Dockerfile.python.j2
devboiler/templates/docker/docker-compose.node.yml.j2
devboiler/templates/docker/docker-compose.python.yml.j2
devboiler/templates/express/server.js.j2
devboiler/templates/fastapi/main.py.j2
devboiler/templates/flask/app.py.j2
devboiler/templates/html/page.html.j2
devboiler/templates/linters/flake8.j2
devboiler/templates/node/index.js.j2
devboiler/templates/poetry/pyproject.toml.j2
devboiler/templates/precommit/config.yaml.j2
devboiler/templates/project/python/init.py.j2
devboiler/templates/project/python/main.py.j2
devboiler/templates/python/class.py.j2
devboiler/templates/python/cli.py.j2
devboiler/templates/react/component_class.jsx.j2
devboiler/templates/react/component_css.module.css.j2
devboiler/templates/react/component_function.jsx.j2
devboiler/templates/react/component_with_css.jsx.j2
devboiler/templates/tests/pytest.ini.j2
devboiler/templates/tests/test_app_fastapi.py.j2
devboiler/templates/tests/test_app_flask.py.j2
devboiler/templates/tests/test_app_python.py.j2
devboiler-0.4.0.dist-info/licenses/LICENSE
devboiler-0.4.0.dist-info/METADATA
devboiler-0.4.0.dist-info/WHEEL
devboiler-0.4.0.dist-info/entry_points.txt
devboiler-0.4.0.dist-info/top_level.txt
devboiler-0.4.0.dist-info/RECORD
