Metadata-Version: 2.4
Name: devboiler
Version: 0.4.0
Summary: Generate boilerplate for apps, web pages, and components.
Author: mir0swag, kotekfrozi
License-Expression: MIT
Project-URL: Homepage, https://github.com/mir0swag/devboiler
Project-URL: Repository, https://github.com/mir0swag/devboiler
Keywords: boilerplate,scaffold,cli,templates,generator
Classifier: Programming Language :: Python :: 3
Classifier: Programming Language :: Python :: 3 :: Only
Classifier: Operating System :: OS Independent
Classifier: Environment :: Console
Classifier: Topic :: Software Development :: Code Generators
Requires-Python: >=3.8
License-File: LICENSE
Requires-Dist: Jinja2>=3.1
Dynamic: license-file
